flask_checkr/__about__.py
flask_checkr/__init__.py
flask_checkr/errors.py
flask_checkr/schema.py
flask_checkr-0.1.2.dist-info/WHEEL
flask_checkr-0.1.2.dist-info/METADATA
flask_checkr-0.1.2.dist-info/RECORD
